edge_st_sdk/__init__.py
edge_st_sdk/edge_client.py
edge_st_sdk/aws/__init__.py
edge_st_sdk/aws/aws_client.py
edge_st_sdk/aws/aws_greengrass.py
edge_st_sdk/azure/__init__.py
edge_st_sdk/azure/azure_client.py
edge_st_sdk/azure/azure_utils.py
edge_st_sdk/utils/__init__.py
edge_st_sdk/utils/edge_st_exceptions.py
edge_st_sdk/utils/python_utils.py
edge_st_sdk_package-1.0.28.dist-info/LICENSE
edge_st_sdk_package-1.0.28.dist-info/METADATA
edge_st_sdk_package-1.0.28.dist-info/WHEEL
edge_st_sdk_package-1.0.28.dist-info/top_level.txt
edge_st_sdk_package-1.0.28.dist-info/RECORD
